rasm.py
rasm-0.1.1.dist-info/METADATA
rasm-0.1.1.dist-info/WHEEL
rasm-0.1.1.dist-info/entry_points.txt
rasm-0.1.1.dist-info/top_level.txt
rasm-0.1.1.dist-info/RECORD
