Metadata-Version: 2.1
Name: rasm
Version: 0.1.1
Summary: Assembler for 8-bit AVR microcontrollers
Home-page: https://github.com/raek/rasm
Author: Rasmus Bondesson
Author-email: raek@raek.se
License: MIT
Platform: UNKNOWN
Classifier: Development Status :: 3 - Alpha
Classifier: Intended Audience :: Developers
Classifier: License :: OSI Approved :: MIT License
Classifier: Programming Language :: Assembly
Classifier: Topic :: Software Development :: Assemblers
Classifier: Topic :: Software Development :: Embedded Systems
Requires-Python: >=3.6
